{
    "id": 82233537,
    "name": "dc challenge",
    "author": "LucasWX",
    "creators": ["LucasWX"],
    "verifier": "LucasWX",
    "verification": "NONE",
    "percentToQualify": 50,
    "password": "Unknown",
    "records": [
        {
            "user": "Throwbie",
            "link": "None",
            "percent": 100,
            "hz": 0
        },
        {
            "user": "Rsnobal",
            "link": "https://media.discordapp.net/attachments/1003438270077751549/1282939860126273536/dc_challenge_100.mp4?ex=66e12e5a&is=66dfdcda&hm=67f67527b3888c5fe4692a04ef57abdd91cdc1f73ad1118d213ea9c2c1ac73a0&",
            "percent": 100,
            "hz": 165
        }
      
    ]
}
